deepx/__init__.py
deepx/_info.py
deepx/_version.py
deepx_pack-1.0.6.post3.dist-info/licenses/LICENSE
deepx_pack-1.0.6.post3.dist-info/METADATA
deepx_pack-1.0.6.post3.dist-info/WHEEL
deepx_pack-1.0.6.post3.dist-info/entry_points.txt
deepx_pack-1.0.6.post3.dist-info/top_level.txt
deepx_pack-1.0.6.post3.dist-info/RECORD
