Metadata-Version: 2.4
Name: deepx-pack
Version: 1.0.6.post3
Summary: DeepH-pack is a general-purpose neural network package for deep-learning electronic structure calculations. As the latest evolution of the DeepH framework, it integrates all prior methodologies into a unified, cohesive toolkit. This enhanced version has been fully rebuilt using JAX, delivering greater computational efficiency and expanded functionality.
Author-email: DeepH team <deeph-pack@outlook.com>
License-Expression: GPL-3.0-or-later
Project-URL: Repository, https://github.com/kYangLi/DeepH-pack-docs.git
Keywords: DeepH-pack,DeepH,Physics,Deep Learning,Graph Neural Network,JAX
Classifier: Development Status :: 5 - Production/Stable
Classifier: Programming Language :: Python :: 3.13
Requires-Python: <3.15,>=3.13
License-File: LICENSE
Requires-Dist: pyarmor==9.1.9
Requires-Dist: numpy
Requires-Dist: toml
Requires-Dist: h5py
Requires-Dist: matplotlib
Requires-Dist: joblib
Requires-Dist: rocksdict
Provides-Extra: gpu
Requires-Dist: torch==2.7.1+cpu; extra == "gpu"
Requires-Dist: torch_geometric==2.6.1; extra == "gpu"
Requires-Dist: jax[cuda12]==0.6.2; extra == "gpu"
Requires-Dist: flax==0.10.6; extra == "gpu"
Requires-Dist: e3nn-jax==0.20.7; extra == "gpu"
Requires-Dist: optax==0.2.5; extra == "gpu"
Requires-Dist: orbax-checkpoint==0.11.16; extra == "gpu"
Provides-Extra: cpu
Requires-Dist: torch==2.7.1+cpu; extra == "cpu"
Requires-Dist: torch_geometric==2.6.1; extra == "cpu"
Requires-Dist: jax[cpu]==0.6.2; extra == "cpu"
Requires-Dist: flax==0.10.6; extra == "cpu"
Requires-Dist: e3nn-jax==0.20.7; extra == "cpu"
Requires-Dist: optax==0.2.5; extra == "cpu"
Requires-Dist: orbax-checkpoint==0.11.16; extra == "cpu"
Provides-Extra: julia
Requires-Dist: cython; extra == "julia"
Requires-Dist: juliacall; extra == "julia"
Provides-Extra: mpi
Requires-Dist: mpi4py; extra == "mpi"
Provides-Extra: mpi4jax
Requires-Dist: cython; extra == "mpi4jax"
Requires-Dist: mpi4jax==0.7.1; extra == "mpi4jax"
Provides-Extra: docs
Requires-Dist: sphinx; extra == "docs"
Requires-Dist: sphinx-book-theme; extra == "docs"
Requires-Dist: sphinx-autobuild; extra == "docs"
Requires-Dist: ipykernel; extra == "docs"
Requires-Dist: myst_nb; extra == "docs"
Requires-Dist: nbstripout; extra == "docs"
Requires-Dist: recommonmark; extra == "docs"
Requires-Dist: ipython_genutils; extra == "docs"
Requires-Dist: sphinx-design; extra == "docs"
Requires-Dist: jupytext; extra == "docs"
Requires-Dist: docutils; extra == "docs"
Dynamic: license-file
